marshmallow_utils/__init__.py
marshmallow_utils/html.py
marshmallow_utils/links.py
marshmallow_utils/permissions.py
marshmallow_utils/fields/__init__.py
marshmallow_utils/fields/babel.py
marshmallow_utils/fields/contrib.py
marshmallow_utils/fields/edtfdatestring.py
marshmallow_utils/fields/generated.py
marshmallow_utils/fields/identifier.py
marshmallow_utils/fields/isodate.py
marshmallow_utils/fields/isolanguage.py
marshmallow_utils/fields/links.py
marshmallow_utils/fields/nestedattr.py
marshmallow_utils/fields/sanitizedhtml.py
marshmallow_utils/fields/sanitizedunicode.py
marshmallow_utils/fields/strippedhtml.py
marshmallow_utils/fields/trimmed.py
marshmallow_utils/fields/tzdatetime.py
marshmallow_utils/fields/url.py
marshmallow_utils/schemas/__init__.py
marshmallow_utils/schemas/geojson.py
marshmallow_utils/schemas/identifier.py
marshmallow_utils/translations/messages.pot
marshmallow_utils/translations/ar/LC_MESSAGES/messages.po
marshmallow_utils/translations/bg/LC_MESSAGES/messages.po
marshmallow_utils/translations/ca/LC_MESSAGES/messages.po
marshmallow_utils/translations/cs/LC_MESSAGES/messages.po
marshmallow_utils/translations/da/LC_MESSAGES/messages.po
marshmallow_utils/translations/de/LC_MESSAGES/messages.po
marshmallow_utils/translations/el/LC_MESSAGES/messages.po
marshmallow_utils/translations/es/LC_MESSAGES/messages.po
marshmallow_utils/translations/et/LC_MESSAGES/messages.po
marshmallow_utils/translations/fa/LC_MESSAGES/messages.po
marshmallow_utils/translations/fi/LC_MESSAGES/messages.po
marshmallow_utils/translations/fr/LC_MESSAGES/messages.po
marshmallow_utils/translations/hr/LC_MESSAGES/messages.po
marshmallow_utils/translations/hu/LC_MESSAGES/messages.po
marshmallow_utils/translations/it/LC_MESSAGES/messages.po
marshmallow_utils/translations/ja/LC_MESSAGES/messages.po
marshmallow_utils/translations/ka/LC_MESSAGES/messages.po
marshmallow_utils/translations/ko/LC_MESSAGES/messages.po
marshmallow_utils/translations/lt/LC_MESSAGES/messages.po
marshmallow_utils-0.13.1.dist-info/licenses/AUTHORS.rst
marshmallow_utils-0.13.1.dist-info/licenses/LICENSE
marshmallow_utils-0.13.1.dist-info/METADATA
marshmallow_utils-0.13.1.dist-info/WHEEL
marshmallow_utils-0.13.1.dist-info/entry_points.txt
marshmallow_utils-0.13.1.dist-info/top_level.txt
marshmallow_utils-0.13.1.dist-info/RECORD
