Metadata-Version: 2.4
Name: marshmallow-utils
Version: 0.13.1
Summary: Extras and utilities for Marshmallow.
Home-page: https://github.com/inveniosoftware/marshmallow-utils
Author: CERN
Author-email: info@inveniosoftware.org
License: MIT
Keywords: invenio search ui
Platform: any
Classifier: Development Status :: 5 - Production/Stable
Requires-Python: >=3.7
License-File: LICENSE
License-File: AUTHORS.rst
Requires-Dist: arrow>=0.16.0
Requires-Dist: Babel>=2.8
Requires-Dist: babel-edtf>=1.2.0
Requires-Dist: bleach[css]>=5.0.0
Requires-Dist: edtf<6.0.0,>=5.0.0
Requires-Dist: ftfy>=4.4.3
Requires-Dist: geojson>=2.5.0
Requires-Dist: idutils>=1.1.8
Requires-Dist: marshmallow<4.0.0,>=3.5.0
Requires-Dist: marshmallow-oneofschema>=2.1.0
Requires-Dist: pycountry>=18.12.8
Requires-Dist: uritemplate>=3.0.1
Requires-Dist: werkzeug>=1.0.0
Provides-Extra: tests
Requires-Dist: pytest-black-ng>=0.4.0; extra == "tests"
Requires-Dist: check-manifest>=0.42; extra == "tests"
Requires-Dist: coverage>=5.2.1; extra == "tests"
Requires-Dist: pytest-cov>=2.10.1; extra == "tests"
Requires-Dist: pytest-isort>=1.2.0; extra == "tests"
Requires-Dist: pytest-pydocstyle>=2.2.0; extra == "tests"
Requires-Dist: pytest>=6.0; extra == "tests"
Requires-Dist: Sphinx>=4.2.0; extra == "tests"
Dynamic: license-file
